redactdump/__init__.py
redactdump/app.py
redactdump/core/__init__.py
redactdump/core/config.py
redactdump/core/database.py
redactdump/core/file.py
redactdump/core/models.py
redactdump/core/redactor.py
redactdump-0.4.0.dist-info/LICENSE
redactdump-0.4.0.dist-info/METADATA
redactdump-0.4.0.dist-info/NOTICE
redactdump-0.4.0.dist-info/WHEEL
redactdump-0.4.0.dist-info/entry_points.txt
redactdump-0.4.0.dist-info/top_level.txt
redactdump-0.4.0.dist-info/RECORD
