Metadata-Version: 2.1
Name: redactdump
Version: 0.4.0
Summary: redactdump
Home-page: https://github.com/math280h/redactdump
Author: math280h
License: UNKNOWN
Platform: UNKNOWN
License-File: LICENSE
License-File: NOTICE
Requires-Dist: rich (==10.15.2)
Requires-Dist: PyYAML (==6.0)
Requires-Dist: schema (==0.7.5)
Requires-Dist: configargparse (==1.5.3)
Requires-Dist: SQLAlchemy (~=1.4.27)
Requires-Dist: psycopg2-binary (==2.9.3)
Requires-Dist: pymysql (==1.0.2)
Requires-Dist: faker (==10.0.0)
